[
    {
        "name": "PINK MULTIMOJI .925 BRACELET LINK",
        "price": "60.00€",
        "url": "https://www.vinsi72.com/product/multimoji-925-bracelet-link",
        "img": "https://assets.bigcartel.com/product_images/410644197/ecom_multimoji_pink_1.jpg?auto=format&fit=max&w=200"
    },
    {
        "name": "RANGLAN HOODIE BLUE",
        "price": "50.00€",
        "url": "https://www.vinsi72.com/product/ranglan-hoodie-blue",
        "img": "https://assets.bigcartel.com/product_images/410642706/ecom_hoodie_blue_1_1.jpg?auto=format&fit=max&w=200"
    },
    {
        "name": "RANGLAN HOODIE PINK",
        "price": "50.00€",
        "url": "https://www.vinsi72.com/product/ranglan-hoodie-pink",
        "img": "https://assets.bigcartel.com/product_images/410642535/ecom_hoodie_pink_1_1.jpg?auto=format&fit=max&w=200"
    },
    {
        "name": "RANGLAN HOODIE BLACK",
        "price": "50.00€",
        "url": "https://www.vinsi72.com/product/ranglan-hoodie-black",
        "img": "https://assets.bigcartel.com/product_images/410642526/ecom_hoodie_black_1_1.jpg?auto=format&fit=max&w=200"
    },
    {
        "name": "REALTREE RHINESTONE CAMO CAP",
        "price": "39.00€",
        "url": "https://www.vinsi72.com/product/realtree-rhinestone-camo-cap",
        "img": "https://assets.bigcartel.com/product_images/410661216/ecom_realtreecap_1.jpg?auto=format&fit=max&w=200"
    },
    {
        "name": "PURPLE RUBBER TOY NECKLACE",
        "price": "12.00€",
        "url": "https://www.vinsi72.com/product/purple-rubber-toy-necklace",
        "img": "https://assets.bigcartel.com/product_images/353380330/purp_closeup.png?auto=format&fit=max&w=200"
    }
]